superduper_llamacpp/__init__.py
superduper_llamacpp/model.py
superduper_llamacpp-0.10.0.dist-info/licenses/LICENSE
superduper_llamacpp-0.10.0.dist-info/METADATA
superduper_llamacpp-0.10.0.dist-info/WHEEL
superduper_llamacpp-0.10.0.dist-info/top_level.txt
superduper_llamacpp-0.10.0.dist-info/RECORD
